tests/__init__.py
tests/test_config_service.py
tests/test_feature.py
toggler/__init__.py
toggler/exceptions.py
toggler/model.py
toggler/toggler.py
toggler/types.py
toggler/services/__init__.py
toggler/services/config.py
toggler/services/env.py
toggler-0.3.0.dist-info/METADATA
toggler-0.3.0.dist-info/WHEEL
toggler-0.3.0.dist-info/top_level.txt
toggler-0.3.0.dist-info/RECORD
