Metadata-Version: 2.1
Name: toggler
Version: 0.3.0
Summary: Feature Flags Manager
Home-page: https://github.com/versada/toggler
Author: Versada (Andrius Laukavičius)
Author-email: andrius.laukavicius@versada.eu
License: LGPLv3
Classifier: Intended Audience :: Developers
Classifier: Natural Language :: English
Classifier: Programming Language :: Python
Classifier: Programming Language :: Python :: 3
Classifier: Programming Language :: Python :: 3.10
Classifier: Programming Language :: Python :: 3.11
Classifier: Programming Language :: Python :: 3.12
Classifier: Programming Language :: Python :: Implementation :: CPython
Classifier: Programming Language :: Python :: Implementation :: PyPy
Requires-Dist: pyyaml ==6.0.1
Requires-Dist: mergedeep ==1.3.4
Provides-Extra: test
Requires-Dist: pytest ; extra == 'test'
